simio_lisa/__init__.py
simio_lisa/experiments.py
simio_lisa/load_simio_project.py
simio_lisa/simio_plots.py
simio_lisa/simio_tables.py
simio_lisa/utils.py
simio_lisa-2.0.0.dist-info/LICENSE
simio_lisa-2.0.0.dist-info/METADATA
simio_lisa-2.0.0.dist-info/WHEEL
simio_lisa-2.0.0.dist-info/top_level.txt
simio_lisa-2.0.0.dist-info/RECORD
