Metadata-Version: 2.1
Name: simio-lisa
Version: 2.0.0
Summary: Beautiful Simio: Importing data and powering viz.
Home-page: https://github.com/mielgosez/simio_lisa
Author: Jose Mielgo, Alessandro Seri
Author-email: mielgosez@gmail.com, seri.alessandro@gmail.com
License: UNKNOWN
Project-URL: Bug Tracker, https://github.com/mielgosez/simio_lisa/issues
Platform: UNKNOWN
Classifier: Programming Language :: Python :: 3
Classifier: License :: OSI Approved :: MIT License
Classifier: Operating System :: OS Independent
Requires-Python: >=3.6
License-File: LICENSE
Requires-Dist: pandas
Requires-Dist: numpy
Requires-Dist: plotly
